HoneyPi-0.0.1.dist-info/top_level.txt
HoneyPi-0.0.1.dist-info/METADATA
HoneyPi-0.0.1.dist-info/metadata.json
HoneyPi-0.0.1.dist-info/WHEEL
HoneyPi-0.0.1.dist-info/RECORD
HoneyPi-0.0.1.dist-info/DESCRIPTION.rst
HoneyPi/core.py
HoneyPi/__init__.py
