Metadata-Version: 2.0
Name: HoneyPi
Version: 0.0.1
Summary: HoneyPi is a package for Python that let's you automatically notify your honey when your working later - as you only need to fix this one last siiiiimple bug!
Home-page: https://github.com/matsbauer/HoneyPi
Author: Mats Bauer
Author-email: contact@airlibi.com
License: MIT
Keywords: python automation honey notice
Platform: UNKNOWN
